README.rst
setup.py
pytest_extra/__init__.py
pytest_extra.egg-info/PKG-INFO
pytest_extra.egg-info/SOURCES.txt
pytest_extra.egg-info/dependency_links.txt
pytest_extra.egg-info/top_level.txt