Metadata-Version: 1.0
Name: pytest-extra
Version: 0.1
Summary: Some helpers for writing tests with pytest.
Home-page: http://github.com/mbr/pytest_extra
Author: Marc Brinkmann
Author-email: git@marcbrinkmann.de
License: MIT
Platform: UNKNOWN
